checker/__init__.py
checker/admin.py
checker/apps.py
checker/forms.py
checker/models.py
checker/tests.py
checker/urls.py
checker/views.py
checker/migrations/0001_initial.py
checker/migrations/0002_remove_websitecheck_content_and_more.py
checker/migrations/0003_remove_websitecheck_screenshot_filename_and_more.py
checker/migrations/__init__.py
website_checker/__init__.py
website_checker/__main__.py
website_checker/asgi.py
website_checker/cli.py
website_checker/settings.py
website_checker/urls.py
website_checker/wsgi.py
website_checker/__pycache__/__init__.cpython-310.pyc
website_checker/__pycache__/settings.cpython-310.pyc
website_checker/__pycache__/urls.cpython-310.pyc
website_checker/__pycache__/wsgi.cpython-310.pyc
website_checker/checker/__init__.py
website_checker/checker/admin.py
website_checker/checker/apps.py
website_checker/checker/forms.py
website_checker/checker/models.py
website_checker/checker/urls.py
website_checker/checker/views.py
ianotech_webchecker-1.0.3.dist-info/METADATA
ianotech_webchecker-1.0.3.dist-info/WHEEL
ianotech_webchecker-1.0.3.dist-info/entry_points.txt
ianotech_webchecker-1.0.3.dist-info/top_level.txt
ianotech_webchecker-1.0.3.dist-info/RECORD
