Metadata-Version: 2.4
Name: ianotech-webchecker
Version: 1.0.3
Summary: A Django app to check website status with screenshots
Author: IanoTech
Requires-Dist: Django>=4.0
Requires-Dist: requests>=2.25.0
Dynamic: author
Dynamic: requires-dist
Dynamic: summary
